c2net/__init__.py
c2net/context/__init__.py
c2net/context/context.py
c2net/context/download.py
c2net/context/env_check.py
c2net/context/helper.py
c2net/context/moxing_env_check.py
c2net/context/moxing_helper.py
c2net/context/upload.py
c2net/utils/__init__.py
c2net/utils/constants.py
c2net/utils/logger.py
c2net/utils/util.py
c2net_beta-0.2.5.dist-info/METADATA
c2net_beta-0.2.5.dist-info/WHEEL
c2net_beta-0.2.5.dist-info/top_level.txt
c2net_beta-0.2.5.dist-info/RECORD
