Metadata-Version: 2.1
Name: c2net-beta
Version: 0.2.5
Summary: A test package for c2net pypi
Home-page: https://openi.pcl.ac.cn/liuzx/c2net-pypi
Author: liuzx
Author-email: gsunfeng@163.com
License: MIT
Platform: UNKNOWN
Classifier: License :: OSI Approved :: MIT License
Classifier: Intended Audience :: Developers
Classifier: Topic :: Software Development :: Build Tools
Classifier: Operating System :: OS Independent
